{"samples": 106, "value": [97.0, 71.0], "label": "pct_total_to_AFG <= 0.000010", "type": "split", "feature": "pct_total_to_AFG", "threshold": 0.000010, "children": [{"samples": 44, "value": [59.0, 6.0], "label": "pct_doi_total_to_GBR <= 0.002908", "type": "split", "feature": "pct_doi_total_to_GBR", "threshold": 0.002908, "children": [{"samples": 41, "value": [58.0, 2.0], "label": "pct_dod_total_to_JOR <= 0.000646", "type": "split", "feature": "pct_dod_total_to_JOR", "threshold": 0.000646, "children": [{"samples": 39, "value": [58.0, 0.0], "label": "Leaf - 3", "type": "leaf"}, {"samples": 2, "value": [0.0, 2.0], "label": "Leaf - 4", "type": "leaf"}]}, {"samples": 3, "value": [1.0, 4.0], "label": "pct_dos_total_to_BGD <= 0.000423", "type": "split", "feature": "pct_dos_total_to_BGD", "threshold": 0.000423, "children": [{"samples": 2, "value": [0.0, 4.0], "label": "Leaf - 6", "type": "leaf"}, {"samples": 1, "value": [1.0, 0.0], "label": "Leaf - 7", "type": "leaf"}]}]}, {"samples": 62, "value": [38.0, 65.0], "label": "pct_hhs_total_to_CAN <= 0.000199", "type": "split", "feature": "pct_hhs_total_to_CAN", "threshold": 0.000199, "children": [{"samples": 32, "value": [12.0, 43.0], "label": "pct_dod_total_to_ARE <= 0.003262", "type": "split", "feature": "pct_dod_total_to_ARE", "threshold": 0.003262, "children": [{"samples": 13, "value": [10.0, 9.0], "label": "pct_dos_total_to_AZE <= 0.000033", "type": "split", "feature": "pct_dos_total_to_AZE", "threshold": 0.000033, "children": [{"samples": 9, "value": [3.0, 9.0], "label": "pct_total_to_XKS <= 0.000002", "type": "split", "feature": "pct_total_to_XKS", "threshold": 0.000002, "children": [{"samples": 7, "value": [1.0, 9.0], "label": "pct_dos_total_to_CHE <= -0.000006", "type": "split", "feature": "pct_dos_total_to_CHE", "threshold": -0.000006, "children": [{"samples": 1, "value": [1.0, 0.0], "label": "Leaf - 13", "type": "leaf"}, {"samples": 6, "value": [0.0, 9.0], "label": "Leaf - 14", "type": "leaf"}]}, {"samples": 2, "value": [2.0, 0.0], "label": "Leaf - 15", "type": "leaf"}]}, {"samples": 4, "value": [7.0, 0.0], "label": "Leaf - 16", "type": "leaf"}]}, {"samples": 19, "value": [2.0, 34.0], "label": "pct_usda_total_to_JPN <= 0.000005", "type": "split", "feature": "pct_usda_total_to_JPN", "threshold": 0.000005, "children": [{"samples": 18, "value": [1.0, 34.0], "label": "pct_dos_total_to_PER <= 0.000676", "type": "split", "feature": "pct_dos_total_to_PER", "threshold": 0.000676, "children": [{"samples": 17, "value": [0.0, 34.0], "label": "Leaf - 19", "type": "leaf"}, {"samples": 1, "value": [1.0, 0.0], "label": "Leaf - 20", "type": "leaf"}]}, {"samples": 1, "value": [1.0, 0.0], "label": "Leaf - 21", "type": "leaf"}]}]}, {"samples": 30, "value": [26.0, 22.0], "label": "pct_total_to_THA <= 0.000034", "type": "split", "feature": "pct_total_to_THA", "threshold": 0.000034, "children": [{"samples": 12, "value": [5.0, 16.0], "label": "pct_hhs_total_to_ISR <= 0.000013", "type": "split", "feature": "pct_hhs_total_to_ISR", "threshold": 0.000013, "children": [{"samples": 10, "value": [2.0, 16.0], "label": "pct_hhs_total_to_KAZ <= 0.000005", "type": "split", "feature": "pct_hhs_total_to_KAZ", "threshold": 0.000005, "children": [{"samples": 9, "value": [0.0, 16.0], "label": "Leaf - 25", "type": "leaf"}, {"samples": 1, "value": [2.0, 0.0], "label": "Leaf - 26", "type": "leaf"}]}, {"samples": 2, "value": [3.0, 0.0], "label": "Leaf - 27", "type": "leaf"}]}, {"samples": 18, "value": [21.0, 6.0], "label": "pct_dos_total_to_NGA <= 0.000006", "type": "split", "feature": "pct_dos_total_to_NGA", "threshold": 0.000006, "children": [{"samples": 11, "value": [11.0, 6.0], "label": "pct_foreign_hhs <= 0.009722", "type": "split", "feature": "pct_foreign_hhs", "threshold": 0.009722, "children": [{"samples": 7, "value": [11.0, 2.0], "label": "pct_dod_total_to_THA <= 0.000001", "type": "split", "feature": "pct_dod_total_to_THA", "threshold": 0.000001, "children": [{"samples": 1, "value": [0.0, 2.0], "label": "Leaf - 31", "type": "leaf"}, {"samples": 6, "value": [11.0, 0.0], "label": "Leaf - 32", "type": "leaf"}]}, {"samples": 4, "value": [0.0, 4.0], "label": "Leaf - 33", "type": "leaf"}]}, {"samples": 7, "value": [10.0, 0.0], "label": "Leaf - 34", "type": "leaf"}]}]}]}]}