{"samples": 168, "value": [101.0, 67.0], "label": "pct_dos_total_to_AGO <= 0.000025", "type": "split", "feature": "pct_dos_total_to_AGO", "threshold": 0.000025, "children": [{"samples": 152, "value": [85.0, 67.0], "label": "pct_dos_total_to_GBR <= 0.000559", "type": "split", "feature": "pct_dos_total_to_GBR", "threshold": 0.000559, "children": [{"samples": 69, "value": [25.0, 44.0], "label": "pct_foreign <= 0.020283", "type": "split", "feature": "pct_foreign", "threshold": 0.020283, "children": [{"samples": 11, "value": [10.0, 1.0], "label": "pct_treas_total_to_USA <= 0.998558", "type": "split", "feature": "pct_treas_total_to_USA", "threshold": 0.998558, "children": [{"samples": 9, "value": [9.0, 0.0], "label": "Leaf - 4", "type": "leaf"}, {"samples": 2, "value": [1.0, 1.0], "label": "pct_doc_total_to_RUS <= 0.000443", "type": "split", "feature": "pct_doc_total_to_RUS", "threshold": 0.000443, "children": [{"samples": 1, "value": [0.0, 1.0], "label": "Leaf - 6", "type": "leaf"}, {"samples": 1, "value": [1.0, 0.0], "label": "Leaf - 7", "type": "leaf"}]}]}, {"samples": 58, "value": [15.0, 43.0], "label": "pct_dhs_total_to_PAN <= 0.000013", "type": "split", "feature": "pct_dhs_total_to_PAN", "threshold": 0.000013, "children": [{"samples": 39, "value": [3.0, 36.0], "label": "pct_dod_total_to_USA <= 0.972415", "type": "split", "feature": "pct_dod_total_to_USA", "threshold": 0.972415, "children": [{"samples": 36, "value": [1.0, 35.0], "label": "total_dod <= 12476053504.000000", "type": "split", "feature": "total_dod", "threshold": 12476053504.000000, "children": [{"samples": 1, "value": [1.0, 0.0], "label": "Leaf - 11", "type": "leaf"}, {"samples": 35, "value": [0.0, 35.0], "label": "Leaf - 12", "type": "leaf"}]}, {"samples": 3, "value": [2.0, 1.0], "label": "pct_total_to_XKS <= 0.000000", "type": "split", "feature": "pct_total_to_XKS", "threshold": 0.000000, "children": [{"samples": 2, "value": [2.0, 0.0], "label": "Leaf - 14", "type": "leaf"}, {"samples": 1, "value": [0.0, 1.0], "label": "Leaf - 15", "type": "leaf"}]}]}, {"samples": 19, "value": [12.0, 7.0], "label": "pct_dod_total_to_UMI <= 0.000000", "type": "split", "feature": "pct_dod_total_to_UMI", "threshold": 0.000000, "children": [{"samples": 16, "value": [12.0, 4.0], "label": "pct_va_total_to_NLD <= 0.000003", "type": "split", "feature": "pct_va_total_to_NLD", "threshold": 0.000003, "children": [{"samples": 13, "value": [11.0, 2.0], "label": "pct_total_to_SWZ <= 0.000006", "type": "split", "feature": "pct_total_to_SWZ", "threshold": 0.000006, "children": [{"samples": 12, "value": [11.0, 1.0], "label": "Leaf - 19", "type": "leaf"}, {"samples": 1, "value": [0.0, 1.0], "label": "Leaf - 20", "type": "leaf"}]}, {"samples": 3, "value": [1.0, 2.0], "label": "pct_ed_total_to_USA <= 0.999966", "type": "split", "feature": "pct_ed_total_to_USA", "threshold": 0.999966, "children": [{"samples": 2, "value": [0.0, 2.0], "label": "Leaf - 22", "type": "leaf"}, {"samples": 1, "value": [1.0, 0.0], "label": "Leaf - 23", "type": "leaf"}]}]}, {"samples": 3, "value": [0.0, 3.0], "label": "Leaf - 24", "type": "leaf"}]}]}]}, {"samples": 83, "value": [60.0, 23.0], "label": "pct_dos_total_to_NLD <= 0.000002", "type": "split", "feature": "pct_dos_total_to_NLD", "threshold": 0.000002, "children": [{"samples": 48, "value": [41.0, 7.0], "label": "pct_hud_total_to_USA <= 1.000020", "type": "split", "feature": "pct_hud_total_to_USA", "threshold": 1.000020, "children": [{"samples": 46, "value": [41.0, 5.0], "label": "pct_total_to_GHA <= 0.000005", "type": "split", "feature": "pct_total_to_GHA", "threshold": 0.000005, "children": [{"samples": 40, "value": [38.0, 2.0], "label": "pct_usda_total_to_PHL <= 0.000012", "type": "split", "feature": "pct_usda_total_to_PHL", "threshold": 0.000012, "children": [{"samples": 39, "value": [38.0, 1.0], "label": "pct_doc_total_to_IND <= 0.000006", "type": "split", "feature": "pct_doc_total_to_IND", "threshold": 0.000006, "children": [{"samples": 37, "value": [37.0, 0.0], "label": "Leaf - 30", "type": "leaf"}, {"samples": 2, "value": [1.0, 1.0], "label": "Leaf - 31", "type": "leaf"}]}, {"samples": 1, "value": [0.0, 1.0], "label": "Leaf - 32", "type": "leaf"}]}, {"samples": 6, "value": [3.0, 3.0], "label": "pct_dod_total_to_JPN <= 0.002428", "type": "split", "feature": "pct_dod_total_to_JPN", "threshold": 0.002428, "children": [{"samples": 3, "value": [3.0, 0.0], "label": "Leaf - 34", "type": "leaf"}, {"samples": 3, "value": [0.0, 3.0], "label": "Leaf - 35", "type": "leaf"}]}]}, {"samples": 2, "value": [0.0, 2.0], "label": "Leaf - 36", "type": "leaf"}]}, {"samples": 35, "value": [19.0, 16.0], "label": "pct_dod_total_to_KHM <= 0.000000", "type": "split", "feature": "pct_dod_total_to_KHM", "threshold": 0.000000, "children": [{"samples": 13, "value": [12.0, 1.0], "label": "pct_dod_total_to_USA <= 0.959738", "type": "split", "feature": "pct_dod_total_to_USA", "threshold": 0.959738, "children": [{"samples": 2, "value": [1.0, 1.0], "label": "pct_dos_total_to_MRT <= -0.000206", "type": "split", "feature": "pct_dos_total_to_MRT", "threshold": -0.000206, "children": [{"samples": 1, "value": [1.0, 0.0], "label": "Leaf - 40", "type": "leaf"}, {"samples": 1, "value": [0.0, 1.0], "label": "Leaf - 41", "type": "leaf"}]}, {"samples": 11, "value": [11.0, 0.0], "label": "Leaf - 42", "type": "leaf"}]}, {"samples": 22, "value": [7.0, 15.0], "label": "pct_dos_total_to_SDN <= 0.000003", "type": "split", "feature": "pct_dos_total_to_SDN", "threshold": 0.000003, "children": [{"samples": 19, "value": [4.0, 15.0], "label": "pct_total_to_LVA <= 0.000009", "type": "split", "feature": "pct_total_to_LVA", "threshold": 0.000009, "children": [{"samples": 16, "value": [2.0, 14.0], "label": "pct_doe_total_to_NOR <= 0.000192", "type": "split", "feature": "pct_doe_total_to_NOR", "threshold": 0.000192, "children": [{"samples": 15, "value": [1.0, 14.0], "label": "Leaf - 46", "type": "leaf"}, {"samples": 1, "value": [1.0, 0.0], "label": "Leaf - 47", "type": "leaf"}]}, {"samples": 3, "value": [2.0, 1.0], "label": "pct_foreign_hhs <= 0.003161", "type": "split", "feature": "pct_foreign_hhs", "threshold": 0.003161, "children": [{"samples": 1, "value": [0.0, 1.0], "label": "Leaf - 49", "type": "leaf"}, {"samples": 2, "value": [2.0, 0.0], "label": "Leaf - 50", "type": "leaf"}]}]}, {"samples": 3, "value": [3.0, 0.0], "label": "Leaf - 51", "type": "leaf"}]}]}]}]}, {"samples": 16, "value": [16.0, 0.0], "label": "Leaf - 52", "type": "leaf"}]}