{"samples": 168, "value": [101.0, 67.0], "label": "pct_foreign <= 0.020403", "type": "split", "feature": "pct_foreign", "threshold": 0.020403, "children": [{"samples": 65, "value": [63.0, 2.0], "label": "pct_doc_total_to_NLD <= 0.005071", "type": "split", "feature": "pct_doc_total_to_NLD", "threshold": 0.005071, "children": [{"samples": 64, "value": [63.0, 1.0], "label": "pct_treas_total_to_GTM <= 0.000077", "type": "split", "feature": "pct_treas_total_to_GTM", "threshold": 0.000077, "children": [{"samples": 57, "value": [57.0, 0.0], "label": "Leaf - 3", "type": "leaf"}, {"samples": 7, "value": [6.0, 1.0], "label": "pct_total_to_GTM <= -0.000000", "type": "split", "feature": "pct_total_to_GTM", "threshold": -0.000000, "children": [{"samples": 1, "value": [0.0, 1.0], "label": "Leaf - 5", "type": "leaf"}, {"samples": 6, "value": [6.0, 0.0], "label": "Leaf - 6", "type": "leaf"}]}]}, {"samples": 1, "value": [0.0, 1.0], "label": "Leaf - 7", "type": "leaf"}]}, {"samples": 103, "value": [38.0, 65.0], "label": "pct_total_to_KEN <= 0.000001", "type": "split", "feature": "pct_total_to_KEN", "threshold": 0.000001, "children": [{"samples": 47, "value": [27.0, 20.0], "label": "pct_dot_total_to_NLD <= 0.000006", "type": "split", "feature": "pct_dot_total_to_NLD", "threshold": 0.000006, "children": [{"samples": 43, "value": [27.0, 16.0], "label": "pct_dol_total_to_USA <= 0.999227", "type": "split", "feature": "pct_dol_total_to_USA", "threshold": 0.999227, "children": [{"samples": 3, "value": [0.0, 3.0], "label": "Leaf - 11", "type": "leaf"}, {"samples": 40, "value": [27.0, 13.0], "label": "pct_total_to_DNK <= 0.000042", "type": "split", "feature": "pct_total_to_DNK", "threshold": 0.000042, "children": [{"samples": 10, "value": [10.0, 0.0], "label": "Leaf - 13", "type": "leaf"}, {"samples": 30, "value": [17.0, 13.0], "label": "pct_total_to_CHN <= 0.000000", "type": "split", "feature": "pct_total_to_CHN", "threshold": 0.000000, "children": [{"samples": 10, "value": [2.0, 8.0], "label": "pct_dhs_total_to_NZL <= 0.000001", "type": "split", "feature": "pct_dhs_total_to_NZL", "threshold": 0.000001, "children": [{"samples": 2, "value": [2.0, 0.0], "label": "Leaf - 16", "type": "leaf"}, {"samples": 8, "value": [0.0, 8.0], "label": "Leaf - 17", "type": "leaf"}]}, {"samples": 20, "value": [15.0, 5.0], "label": "pct_total_to_DEU <= 0.001594", "type": "split", "feature": "pct_total_to_DEU", "threshold": 0.001594, "children": [{"samples": 7, "value": [2.0, 5.0], "label": "Leaf - 19", "type": "leaf"}, {"samples": 13, "value": [13.0, 0.0], "label": "Leaf - 20", "type": "leaf"}]}]}]}]}, {"samples": 4, "value": [0.0, 4.0], "label": "Leaf - 21", "type": "leaf"}]}, {"samples": 56, "value": [11.0, 45.0], "label": "pct_dos_total_to_SEN <= 0.000465", "type": "split", "feature": "pct_dos_total_to_SEN", "threshold": 0.000465, "children": [{"samples": 46, "value": [4.0, 42.0], "label": "pct_total_to_SDN <= 0.000005", "type": "split", "feature": "pct_total_to_SDN", "threshold": 0.000005, "children": [{"samples": 44, "value": [2.0, 42.0], "label": "pct_hhs_total_to_BEL <= 0.000679", "type": "split", "feature": "pct_hhs_total_to_BEL", "threshold": 0.000679, "children": [{"samples": 43, "value": [1.0, 42.0], "label": "pct_hhs_total_to_ZWE <= 0.000011", "type": "split", "feature": "pct_hhs_total_to_ZWE", "threshold": 0.000011, "children": [{"samples": 42, "value": [0.0, 42.0], "label": "Leaf - 26", "type": "leaf"}, {"samples": 1, "value": [1.0, 0.0], "label": "Leaf - 27", "type": "leaf"}]}, {"samples": 1, "value": [1.0, 0.0], "label": "Leaf - 28", "type": "leaf"}]}, {"samples": 2, "value": [2.0, 0.0], "label": "Leaf - 29", "type": "leaf"}]}, {"samples": 10, "value": [7.0, 3.0], "label": "pct_total_to_XKS <= 0.000000", "type": "split", "feature": "pct_total_to_XKS", "threshold": 0.000000, "children": [{"samples": 3, "value": [0.0, 3.0], "label": "Leaf - 31", "type": "leaf"}, {"samples": 7, "value": [7.0, 0.0], "label": "Leaf - 32", "type": "leaf"}]}]}]}]}