{"samples": 168, "value": [101.0, 67.0], "label": "pct_dod_total_to_ARE <= 0.003688", "type": "split", "feature": "pct_dod_total_to_ARE", "threshold": 0.003688, "children": [{"samples": 116, "value": [86.0, 30.0], "label": "pct_total_to_ITA <= 0.000166", "type": "split", "feature": "pct_total_to_ITA", "threshold": 0.000166, "children": [{"samples": 55, "value": [52.0, 3.0], "label": "pct_doj_total_to_PAN <= 0.000002", "type": "split", "feature": "pct_doj_total_to_PAN", "threshold": 0.000002, "children": [{"samples": 54, "value": [52.0, 2.0], "label": "pct_total_to_CHE <= 0.008909", "type": "split", "feature": "pct_total_to_CHE", "threshold": 0.008909, "children": [{"samples": 53, "value": [52.0, 1.0], "label": "pct_total_to_ISR <= 0.000095", "type": "split", "feature": "pct_total_to_ISR", "threshold": 0.000095, "children": [{"samples": 45, "value": [45.0, 0.0], "label": "Leaf - 5", "type": "leaf"}, {"samples": 8, "value": [7.0, 1.0], "label": "pct_dod_total_to_AFG <= 0.000551", "type": "split", "feature": "pct_dod_total_to_AFG", "threshold": 0.000551, "children": [{"samples": 7, "value": [7.0, 0.0], "label": "Leaf - 7", "type": "leaf"}, {"samples": 1, "value": [0.0, 1.0], "label": "Leaf - 8", "type": "leaf"}]}]}, {"samples": 1, "value": [0.0, 1.0], "label": "Leaf - 9", "type": "leaf"}]}, {"samples": 1, "value": [0.0, 1.0], "label": "Leaf - 10", "type": "leaf"}]}, {"samples": 61, "value": [34.0, 27.0], "label": "pct_foreign_dod <= 0.034223", "type": "split", "feature": "pct_foreign_dod", "threshold": 0.034223, "children": [{"samples": 32, "value": [26.0, 6.0], "label": "pct_total_to_RUS <= 0.000001", "type": "split", "feature": "pct_total_to_RUS", "threshold": 0.000001, "children": [{"samples": 2, "value": [0.0, 2.0], "label": "Leaf - 13", "type": "leaf"}, {"samples": 30, "value": [26.0, 4.0], "label": "pct_dos_total_to_BMU <= 0.000266", "type": "split", "feature": "pct_dos_total_to_BMU", "threshold": 0.000266, "children": [{"samples": 29, "value": [26.0, 3.0], "label": "pct_hhs_total_to_ARG <= 0.000109", "type": "split", "feature": "pct_hhs_total_to_ARG", "threshold": 0.000109, "children": [{"samples": 28, "value": [26.0, 2.0], "label": "pct_dod_total_to_PER <= -0.000000", "type": "split", "feature": "pct_dod_total_to_PER", "threshold": -0.000000, "children": [{"samples": 2, "value": [1.0, 1.0], "label": "Leaf - 17", "type": "leaf"}, {"samples": 26, "value": [25.0, 1.0], "label": "Leaf - 18", "type": "leaf"}]}, {"samples": 1, "value": [0.0, 1.0], "label": "Leaf - 19", "type": "leaf"}]}, {"samples": 1, "value": [0.0, 1.0], "label": "Leaf - 20", "type": "leaf"}]}]}, {"samples": 29, "value": [8.0, 21.0], "label": "pct_dod_total_to_KWT <= 0.008755", "type": "split", "feature": "pct_dod_total_to_KWT", "threshold": 0.008755, "children": [{"samples": 23, "value": [3.0, 20.0], "label": "pct_total_to_COG <= 0.000003", "type": "split", "feature": "pct_total_to_COG", "threshold": 0.000003, "children": [{"samples": 21, "value": [1.0, 20.0], "label": "pct_total_to_SYR <= 0.000000", "type": "split", "feature": "pct_total_to_SYR", "threshold": 0.000000, "children": [{"samples": 20, "value": [0.0, 20.0], "label": "Leaf - 24", "type": "leaf"}, {"samples": 1, "value": [1.0, 0.0], "label": "Leaf - 25", "type": "leaf"}]}, {"samples": 2, "value": [2.0, 0.0], "label": "Leaf - 26", "type": "leaf"}]}, {"samples": 6, "value": [5.0, 1.0], "label": "pct_dhs_total_to_FRA <= 0.000048", "type": "split", "feature": "pct_dhs_total_to_FRA", "threshold": 0.000048, "children": [{"samples": 2, "value": [1.0, 1.0], "label": "pct_foreign_doj <= 0.006189", "type": "split", "feature": "pct_foreign_doj", "threshold": 0.006189, "children": [{"samples": 1, "value": [0.0, 1.0], "label": "Leaf - 29", "type": "leaf"}, {"samples": 1, "value": [1.0, 0.0], "label": "Leaf - 30", "type": "leaf"}]}, {"samples": 4, "value": [4.0, 0.0], "label": "Leaf - 31", "type": "leaf"}]}]}]}]}, {"samples": 52, "value": [15.0, 37.0], "label": "pct_dos_total_to_AUT <= 0.000484", "type": "split", "feature": "pct_dos_total_to_AUT", "threshold": 0.000484, "children": [{"samples": 42, "value": [7.0, 35.0], "label": "pct_dod_total_to_NZL <= 0.000043", "type": "split", "feature": "pct_dod_total_to_NZL", "threshold": 0.000043, "children": [{"samples": 37, "value": [3.0, 34.0], "label": "pct_foreign_dhs <= 0.000274", "type": "split", "feature": "pct_foreign_dhs", "threshold": 0.000274, "children": [{"samples": 1, "value": [1.0, 0.0], "label": "Leaf - 35", "type": "leaf"}, {"samples": 36, "value": [2.0, 34.0], "label": "pct_dos_total_to_AUS <= 0.002587", "type": "split", "feature": "pct_dos_total_to_AUS", "threshold": 0.002587, "children": [{"samples": 35, "value": [1.0, 34.0], "label": "pct_dod_total_to_DNK <= 0.000008", "type": "split", "feature": "pct_dod_total_to_DNK", "threshold": 0.000008, "children": [{"samples": 1, "value": [1.0, 0.0], "label": "Leaf - 38", "type": "leaf"}, {"samples": 34, "value": [0.0, 34.0], "label": "Leaf - 39", "type": "leaf"}]}, {"samples": 1, "value": [1.0, 0.0], "label": "Leaf - 40", "type": "leaf"}]}]}, {"samples": 5, "value": [4.0, 1.0], "label": "pct_dos_total_to_PHL <= 0.000063", "type": "split", "feature": "pct_dos_total_to_PHL", "threshold": 0.000063, "children": [{"samples": 1, "value": [0.0, 1.0], "label": "Leaf - 42", "type": "leaf"}, {"samples": 4, "value": [4.0, 0.0], "label": "Leaf - 43", "type": "leaf"}]}]}, {"samples": 10, "value": [8.0, 2.0], "label": "pct_dod_total_to_VNM <= 0.000024", "type": "split", "feature": "pct_dod_total_to_VNM", "threshold": 0.000024, "children": [{"samples": 8, "value": [8.0, 0.0], "label": "Leaf - 45", "type": "leaf"}, {"samples": 2, "value": [0.0, 2.0], "label": "Leaf - 46", "type": "leaf"}]}]}]}